{
  "Course": {
    "Holes": [
      {
        "Lat": -41.231405,
        "Long": 175.475284
      },
      {
        "Lat": -41.228718,
        "Long": 175.480222
      },
      {
        "Lat": -41.226906,
        "Long": 175.477335
      },
      {
        "Lat": -41.228882,
        "Long": 175.478566
      },
      {
        "Lat": -41.230931,
        "Long": 175.475565
      },
      {
        "Lat": -41.230045,
        "Long": 175.476103
      },
      {
        "Lat": -41.228855,
        "Long": 175.472929
      },
      {
        "Lat": -41.228487,
        "Long": 175.471913
      },
      {
        "Lat": -41.225684,
        "Long": 175.474534
      },
      {
        "Lat": -41.227589,
        "Long": 175.471733
      },
      {
        "Lat": -41.225338,
        "Long": 175.474014
      },
      {
        "Lat": -41.22587,
        "Long": 175.475463
      },
      {
        "Lat": -41.22862,
        "Long": 175.473638
      },
      {
        "Lat": -41.226847,
        "Long": 175.475705
      },
      {
        "Lat": -41.229012,
        "Long": 175.474778
      },
      {
        "Lat": -41.229698,
        "Long": 175.476016
      },
      {
        "Lat": -41.226234,
        "Long": 175.475993
      },
      {
        "Lat": -41.228112,
        "Long": 175.472418
      }
    ],
    "Name": "Martinborough"
  }
}